torch_kitti/__init__.py
torch_kitti/_types.py
torch_kitti/common/__init__.py
torch_kitti/common/_data_elem.py
torch_kitti/common/_dataset.py
torch_kitti/depth_completion/__init__.py
torch_kitti/depth_completion/_download.py
torch_kitti/depth_completion/dataset.py
torch_kitti/depth_prediction/__init__.py
torch_kitti/depth_prediction/dataset.py
torch_kitti/metrics/__init__.py
torch_kitti/metrics/functional.py
torch_kitti/raw/__init__.py
torch_kitti/raw/_download.py
torch_kitti/raw/calibration.py
torch_kitti/raw/dataset.py
torch_kitti/raw/inertial_measurement_unit.py
torch_kitti/raw/lidar_point_cloud.py
torch_kitti/raw/synced_rectified/__init__.py
torch_kitti/raw/synced_rectified/_download.py
torch_kitti/raw/synced_rectified/resources/__init__.py
torch_kitti/raw/synced_rectified/resources/drives.pkl
torch_kitti/scripts/__init__.py
torch_kitti/scripts/torch_kitti.py
torch_kitti/transforms/__init__.py
torch_kitti/transforms/_transforms.py
torch_kitti/transforms/functional.py
torch_kitti-1.0.1.dist-info/LICENSE
torch_kitti-1.0.1.dist-info/METADATA
torch_kitti-1.0.1.dist-info/WHEEL
torch_kitti-1.0.1.dist-info/entry_points.txt
torch_kitti-1.0.1.dist-info/top_level.txt
torch_kitti-1.0.1.dist-info/RECORD
