Metadata-Version: 2.1
Name: torch-kitti
Version: 1.0.1
Summary: utilities and pytorch datasets for the KITTI Vision Benchmark Suite
Author: andrea conti
Author-email: andrea.conti@tutanota.com
License: UNKNOWN
Platform: UNKNOWN
Classifier: License :: OSI Approved :: MIT License
Classifier: Programming Language :: Python :: 3
Classifier: Programming Language :: Python :: 3.7
Classifier: Programming Language :: Python :: 3.8
Classifier: Programming Language :: Python :: 3.9
License-File: LICENSE
Requires-Dist: torch (>=1.5.0)
Requires-Dist: torchvision (>=0.6.0)
Requires-Dist: setuptools (>=46.3.0)
Requires-Dist: Pillow (>=7.1.0)
Requires-Dist: requests (>=2.24.0)
Requires-Dist: tqdm (>=4.51.0)
Provides-Extra: dev
Requires-Dist: ipython ; extra == 'dev'
Requires-Dist: pytest ; extra == 'dev'
Requires-Dist: pytest-cov ; extra == 'dev'
Requires-Dist: pre-commit ; extra == 'dev'
Requires-Dist: isort ; extra == 'dev'
Requires-Dist: black ; extra == 'dev'
Requires-Dist: python-language-server ; extra == 'dev'
Requires-Dist: pyls-isort ; extra == 'dev'
Requires-Dist: pyls-black ; extra == 'dev'
Requires-Dist: pyls-mypy ; extra == 'dev'
Requires-Dist: pycodestyle ; extra == 'dev'
Requires-Dist: pyflakes ; extra == 'dev'
Requires-Dist: tox ; extra == 'dev'
